sam_slash_slack/__init__.py
sam_slash_slack/arg_functions.py
sam_slash_slack/arg_types.py
sam_slash_slack/blocks.py
sam_slash_slack/cli.py
sam_slash_slack/exceptions.py
sam_slash_slack/py.typed
sam_slash_slack/signature_verifier.py
sam_slash_slack/slash_slack.py
sam_slash_slack/slash_slack_command.py
sam_slash_slack/slash_slack_request.py
sam_slash_slack-0.1.2.dist-info/LICENSE
sam_slash_slack-0.1.2.dist-info/METADATA
sam_slash_slack-0.1.2.dist-info/WHEEL
sam_slash_slack-0.1.2.dist-info/entry_points.txt
sam_slash_slack-0.1.2.dist-info/top_level.txt
sam_slash_slack-0.1.2.dist-info/RECORD
