Metadata-Version: 2.1
Name: sam-slash-slack
Version: 0.1.2
Summary: A SAM python framework for slack slash bots.
Home-page: https://github.com/henryivesjones/sam-slash-slack
Author-email: Henry Jones <henryivesjones@gmail.com>
License: GPL-3.0-or-later
Keywords: slack,lambda,bot,slash command,aws,sam
Classifier: License :: OSI Approved :: GNU General Public License v3 or later (GPLv3+)
Classifier: Programming Language :: Python :: 3
Classifier: Programming Language :: Python :: 3.7
Classifier: Programming Language :: Python :: 3.8
Classifier: Programming Language :: Python :: 3.9
Classifier: Programming Language :: Python :: 3.10
Classifier: Programming Language :: Python :: 3.11
Requires-Python: >=3.6
License-File: LICENSE
Requires-Dist: aiohttp
Requires-Dist: pydantic
Requires-Dist: boto3
